[
  {
    "id": 20,
    "first_name": "Cemre",
    "last_name": "Yıldız",
    "username": "cemrey",
    "password": "Cemre789!",
    "email": "cemre@gmail.com",
    "phone": "+905327654321",
    "isVerified": true
  },
  {
    "id": 12,
    "first_name": "Selin",
    "last_name": "Ersoy",
    "username": "seline",
    "password": "SelinPass1!",
    "email": "selin@gmail.com",
    "phone": "+905340001111",
    "isVerified": false
  },
  {
    "id": 2,
    "first_name": "Ahmet",
    "last_name": "Yılmaz",
    "username": "ahmety",
    "password": "Sifre123!",
    "email": "ahmet@gmail.com",
    "phone": "+905551112222",
    "isVerified": false
  },
  {
    "id": 3,
    "first_name": "Fatma",
    "last_name": "Kara",
    "username": "fatmak",
    "password": "Guvenli123#",
    "email": "fatma@gmail.com",
    "phone": "+905553334444",
    "isVerified": true
  },
  {
    "id": 21,
    "first_name": "Ali",
    "last_name": "Güneş",
    "username": "alig",
    "password": "Ali1234!",
    "email": "ali@gmail.com",
    "phone": "+905331234567",
    "isVerified": false
  },

  {
    "id": 1,
    "first_name": "Eda",
    "last_name": "Ateş",
    "username": "edates",
    "password": "Furkan123!",
    "email": "edakar@gmail.com",
    "phone": "+14012412405",
    "isVerified": true
  },

  {
    "id": 16,
    "first_name": "Melisa",
    "last_name": "Uçar",
    "username": "melisau",
    "password": "Melisa654!",
    "email": "melisa@gmail.com",
    "phone": "+905387778888",
    "isVerified": true
  },

  {
    "id": 18,
    "first_name": "Naz",
    "last_name": "Bozkurt",
    "username": "nazb",
    "password": "Nazpass1!",
    "email": "naz@gmail.com",
    "phone": "+905308889999",
    "isVerified": true
  },
  {
    "id": 19,
    "first_name": "Yusuf",
    "last_name": "Öztürk",
    "username": "yusufo",
    "password": "Yusuf111!",
    "email": "yusuf@gmail.com",
    "phone": "+905312345678",
    "isVerified": false
  },
  {
    "id": 4,
    "first_name": "Mustafa",
    "last_name": "Aydın",
    "username": "mustafaa",
    "password": "Aa123456!",
    "email": "mustafa@hotmail.com",
    "phone": "+905555556666",
    "isVerified": false
  }
]
